jupyterlab_client/__init__.py
jupyterlab_client/py.typed
jupyterlab_client-0.0.0.dist-info/METADATA
jupyterlab_client-0.0.0.dist-info/WHEEL
jupyterlab_client-0.0.0.dist-info/RECORD
