Metadata-Version: 2.4
Name: jupyterlab-client
Version: 0.0.0
Summary: A Python client library for programmatically interacting with JupyterLab services
Project-URL: Repository, https://github.com/Haskely/jupyterlab-client
Project-URL: Documentation, https://github.com/Haskely/jupyterlab-client#readme
Project-URL: Issue Tracker, https://github.com/Haskely/jupyterlab-client/issues
Project-URL: Changelog, https://github.com/Haskely/jupyterlab-client/blob/main/CHANGELOG.md
Author-email: Haskely <Haskely@live.com>
License-Expression: MIT
Keywords: automation,client,jupyter,jupyterlab,remote
Classifier: Development Status :: 3 - Alpha
Classifier: Intended Audience :: Developers
Classifier: License :: OSI Approved :: MIT License
Classifier: Programming Language :: Python :: 3
Classifier: Programming Language :: Python :: 3.10
Classifier: Programming Language :: Python :: 3.11
Classifier: Programming Language :: Python :: 3.12
Classifier: Topic :: Software Development :: Libraries :: Python Modules
Requires-Python: >=3.10
